syl/__init__.py
syl/cli/__init__.py
syl/cli/create.py
syl/cli/index.py
syl/cli/logs.py
syl/cli/pull.py
syl/cli/query.py
syl/cli/remove.py
syl/cli/restart.py
syl/cli/server.py
syl/cli/start.py
syl/cli/status.py
syl/cli/stop.py
syl/cli/syl.py
syl/cli/watch.py
syl/common/__init__.py
syl/common/colors.py
syl/common/datastores.py
syl/common/docker.py
syl/common/logger.py
syl/common/server_api.py
syl/common/tools.py
syl/containers/__init__.py
syl/containers/index/index.py
syl/containers/server/__init__.py
syl/containers/server/control.py
syl/containers/server/mcp_http_stream.py
syl/containers/server/openai_http.py
syl/containers/server/registrations.py
syl/containers/server/server.py
syl/containers/server/tools.py
syl/containers/watcher/watcher.py
syl/datastores/__init__.py
syl/datastores/chromadb.py
syl/datastores/constants.py
syl/datastores/datastore.py
syl/datastores/pgvector.py
syl/datastores/s3_vector.py
syl/datastores/utils.py
syl/parsers/__init__.py
syl/parsers/go.py
syl/parsers/javascript.py
syl/parsers/parser.py
syl/parsers/python.py
syl-0.1.1.dist-info/METADATA
syl-0.1.1.dist-info/WHEEL
syl-0.1.1.dist-info/entry_points.txt
syl-0.1.1.dist-info/top_level.txt
syl-0.1.1.dist-info/RECORD
