Metadata-Version: 2.4
Name: syl
Version: 0.1.1
Summary: A CLI tool for managing code-search semantic LLM tool projects and dependencies
Author-email: Andy Evans <syl@moog.sh>
License: MIT
Project-URL: Repository, https://gitlab.com/ohtz/syl
Classifier: License :: OSI Approved :: MIT License
Classifier: Programming Language :: Python :: 3.10
Classifier: Programming Language :: Python :: 3.11
Classifier: Programming Language :: Python :: 3.12
Requires-Python: >=3.10
Requires-Dist: tabulate==0.9.0
Requires-Dist: requests<2.33.0
Requires-Dist: loguru<0.8.0
Requires-Dist: pydantic<2.12.0
Requires-Dist: pydantic-settings<2.12.0
Requires-Dist: pydantic_core<2.34.0
Requires-Dist: docker==7.1.0
